prepropy/__init__.py
prepropy/cli.py
prepropy/duplichecker.py
prepropy/nullsense.py
prepropy/scalenpipe.py
prepropy-0.1.0.dist-info/licenses/LICENSE
tests/__init__.py
tests/run_tests.py
tests/test_duplichecker.py
tests/test_nullsense.py
tests/test_scalenpipe.py
prepropy-0.1.0.dist-info/METADATA
prepropy-0.1.0.dist-info/WHEEL
prepropy-0.1.0.dist-info/entry_points.txt
prepropy-0.1.0.dist-info/top_level.txt
prepropy-0.1.0.dist-info/RECORD
